pyw/__init__.py
pyw/logger/__init__.py
pyw_logger-0.0.0.post3.dist-info/METADATA
pyw_logger-0.0.0.post3.dist-info/WHEEL
pyw_logger-0.0.0.post3.dist-info/licenses/LICENSE
pyw_logger-0.0.0.post3.dist-info/RECORD
