Metadata-Version: 2.4
Name: pyw-logger
Version: 0.0.0.post3
Summary: Structured and colorful logging helpers (placeholder)
Project-URL: Homepage, https://github.com/pythonWoods/pyw-logger
Project-URL: Documentation, https://pythonwoods.dev/docs/pyw-logger/latest/
Project-URL: Issues, https://github.com/pythonWoods/pyw-logger/issues
Project-URL: Changelog, https://github.com/pythonWoods/pyw-logger/releases
Author: pythonWoods
License: MIT
License-File: LICENSE
Classifier: Development Status :: 2 - Pre-Alpha
Classifier: License :: OSI Approved :: MIT License
Classifier: Programming Language :: Python :: 3 :: Only
Classifier: Programming Language :: Python :: 3.11
Classifier: Typing :: Typed
Requires-Python: >=3.9
Requires-Dist: pyw-core>=0.0.0
Requires-Dist: rich>=13
Requires-Dist: structlog>=24
